odoo/addons/base_remote/README.rst
odoo/addons/base_remote/__init__.py
odoo/addons/base_remote/__manifest__.py
odoo/addons/base_remote/i18n/base_remote.pot
odoo/addons/base_remote/i18n/es.po
odoo/addons/base_remote/i18n/es_AR.po
odoo/addons/base_remote/i18n/it.po
odoo/addons/base_remote/i18n/tr.po
odoo/addons/base_remote/models/__init__.py
odoo/addons/base_remote/models/base.py
odoo/addons/base_remote/models/res_remote.py
odoo/addons/base_remote/models/res_users.py
odoo/addons/base_remote/readme/CONTRIBUTORS.rst
odoo/addons/base_remote/readme/DESCRIPTION.rst
odoo/addons/base_remote/readme/USAGE.rst
odoo/addons/base_remote/security/ir.model.access.csv
odoo/addons/base_remote/static/description/icon.png
odoo/addons/base_remote/static/description/index.html
odoo/addons/base_remote/tests/__init__.py
odoo/addons/base_remote/tests/test_remote.py
odoo/addons/base_remote/views/res_remote_views.xml
odoo_addon_base_remote-16.0.1.0.3.dist-info/METADATA
odoo_addon_base_remote-16.0.1.0.3.dist-info/WHEEL
odoo_addon_base_remote-16.0.1.0.3.dist-info/top_level.txt
odoo_addon_base_remote-16.0.1.0.3.dist-info/RECORD
